jupyterlab_gpulab/__init__.py
jupyterlab_gpulab/_version.py
jupyterlab_gpulab/handlers.py
jupyterlab_gpulab/labextension/build_log.json
jupyterlab_gpulab/labextension/package.json
jupyterlab_gpulab/labextension/static/322.d6a3c77a1e9e023881f6.js
jupyterlab_gpulab/labextension/static/405.9df4e342cf75a33b97fc.js
jupyterlab_gpulab/labextension/static/44e4ec09eb7cf31553fe731921fa0a78.png
jupyterlab_gpulab/labextension/static/549.9b88d56f6802eedd46f2.js
jupyterlab_gpulab/labextension/static/549.e33d65bc27aea33265a7.js
jupyterlab_gpulab/labextension/static/703.8adc9385410cc46e56c1.js
jupyterlab_gpulab/labextension/static/703.a6a44ddac0f280b3dd39.js
jupyterlab_gpulab/labextension/static/703.ea843289ad0d5d7b5ff0.js
jupyterlab_gpulab/labextension/static/lib_index_js.b001230fb4bf4d6a3f4c.js
jupyterlab_gpulab/labextension/static/lib_index_js.b001230fb4bf4d6a3f4c.js.map
jupyterlab_gpulab/labextension/static/remoteEntry.15a9cf1ba5a59f5ea7c1.js
jupyterlab_gpulab/labextension/static/remoteEntry.15a9cf1ba5a59f5ea7c1.js.map
jupyterlab_gpulab/labextension/static/remoteEntry.20cb299eadbabc8e2a7c.js
jupyterlab_gpulab/labextension/static/remoteEntry.535187e4d437c541e962.js
jupyterlab_gpulab/labextension/static/remoteEntry.6b7ebf8b9657712c70c9.js
jupyterlab_gpulab/labextension/static/style.js
jupyterlab_gpulab/labextension/static/style_index_css.b0c0bf755f9961265992.js
jupyterlab_gpulab/labextension/static/style_index_css.b0c0bf755f9961265992.js.map
jupyterlab_gpulab/labextension/static/vendors-node_modules_css-loader_dist_runtime_api_js-node_modules_css-loader_dist_runtime_cssW-926fd9.bfeba028b48373f5278b.js
jupyterlab_gpulab/labextension/static/vendors-node_modules_css-loader_dist_runtime_api_js-node_modules_css-loader_dist_runtime_cssW-926fd9.bfeba028b48373f5278b.js.map
jupyterlab_gpulab/public/index.html
jupyterlab_gpulab/public/logo.png
jupyterlab_gpustats/__init__.py
jupyterlab_gpustats/_version.py
jupyterlab_gpustats/handlers.py
jupyterlab_gpustats/labextension/build_log.json
jupyterlab_gpustats-1.0.1.dist-info/LICENSE
jupyterlab_gpustats-1.0.1.dist-info/METADATA
jupyterlab_gpustats-1.0.1.dist-info/WHEEL
jupyterlab_gpustats-1.0.1.dist-info/top_level.txt
jupyterlab_gpustats-1.0.1.dist-info/RECORD
